{
    "Survey Name": {
      "Page Name 1": {
        "Question1_Name": {
          "Description": "Description of Question 1",
          "Answers": ["Answer 1", "Answer 2", "Answer 3"]
        },
        "Question2_Name": {
          "Description": "Description of Question 2",
          "Answers": ["Answer 1", "Answer 2", "Answer 3"]
        }
      },
      "Page Name 2": {
        "Question3_Name": {
          "Description": "Description of Question 3",
          "Answers": ["Answer 1", "Answer 2", "Answer 3"]
        }
      }
    }
  }
  